aps_redisdb/__init__.py
aps_redisdb/redis_client.py
aps_redisdb/redis_connection.py
aps_redisdb-1.0.1.dist-info/METADATA
aps_redisdb-1.0.1.dist-info/WHEEL
aps_redisdb-1.0.1.dist-info/top_level.txt
aps_redisdb-1.0.1.dist-info/RECORD
