Metadata-Version: 2.4
Name: aps-redisdb
Version: 1.0.1
Summary: A simple Redis DB client wrapper with YAML config support
Author: Anand
License: MIT
Classifier: Programming Language :: Python :: 3
Classifier: Operating System :: OS Independent
Requires-Python: >=3.7
Requires-Dist: redis
Requires-Dist: pyyaml
Provides-Extra: dev
Requires-Dist: build; extra == "dev"
Requires-Dist: twine; extra == "dev"
